README.md
setup.py
smartnlp/__init__.py
smartnlp.egg-info/PKG-INFO
smartnlp.egg-info/SOURCES.txt
smartnlp.egg-info/dependency_links.txt
smartnlp.egg-info/requires.txt
smartnlp.egg-info/top_level.txt
smartnlp/augmentation/__init__.py
smartnlp/augmentation/eda.py
smartnlp/classfication/__init__.py
smartnlp/classfication/deep_classifier.py
smartnlp/classfication/fasttext_classifier.py
smartnlp/classfication/svm_classifier.py
smartnlp/custom/__init__.py
smartnlp/custom/encoding/__init__.py
smartnlp/custom/encoding/mask_encoder.py
smartnlp/custom/encoding/position_encoder.py
smartnlp/custom/layer/__init__.py
smartnlp/custom/layer/attention.py
smartnlp/custom/layer/decoder.py
smartnlp/custom/layer/decoder_layer.py
smartnlp/custom/layer/encoder.py
smartnlp/custom/layer/encoder_layer.py
smartnlp/custom/learning_rate/__init__.py
smartnlp/custom/learning_rate/learning_rate.py
smartnlp/custom/model/__init__.py
smartnlp/custom/model/seq2seq.py
smartnlp/custom/model/transformer.py
smartnlp/embedding/__init__.py
smartnlp/embedding/embedding.py
smartnlp/embedding/fasttext_model.py
smartnlp/embedding/word2vec.py
smartnlp/generation/__init__.py
smartnlp/generation/deep_generation.py
smartnlp/ner/__init__.py
smartnlp/ner/bilstm_crf.py
smartnlp/nmt/__init__.py
smartnlp/nmt/data_process.py
smartnlp/nmt/evaluator.py
smartnlp/nmt/training.py
smartnlp/simililarity/__init__.py
smartnlp/simililarity/siamese_similarity.py
smartnlp/topic/__init__.py
smartnlp/topic/lda_topic.py
smartnlp/utils/__init__.py
smartnlp/utils/basic_log.py
smartnlp/utils/clean_text.py
smartnlp/utils/loader.py
smartnlp/utils/plot_model_history.py
smartnlp/utils/pre_process.py
smartnlp/utils/stopwords.py